log_to_json/__about__.py
log_to_json/__init__.py
log_to_json/log_to_json.py
log_to_json-0.1.1.dist-info/LICENSE
log_to_json-0.1.1.dist-info/METADATA
log_to_json-0.1.1.dist-info/WHEEL
log_to_json-0.1.1.dist-info/top_level.txt
log_to_json-0.1.1.dist-info/RECORD
