Metadata-Version: 2.1
Name: log-to-json
Version: 0.1.1
Summary: Yet another package to convert log messages to JSON.
Home-page: https://github.com/rwhitt2049/log_to_json
Author: Ry Whittington
Author-email: rwhitt2049@gmail.com
License: MIT license
Keywords: log_to_json,log-to-json,logging,json,logger
Platform: UNKNOWN
Classifier: Development Status :: 4 - Beta
Classifier: Intended Audience :: Developers
Classifier: License :: OSI Approved :: MIT License
Classifier: Natural Language :: English
Classifier: Programming Language :: Python :: 3
Classifier: Programming Language :: Python :: 3.5
Classifier: Programming Language :: Python :: 3.6
Classifier: Programming Language :: Python :: 3.7
Classifier: Programming Language :: Python :: 3.8
Provides-Extra: dev
Requires-Dist: black (==19.10b0) ; extra == 'dev'
Requires-Dist: flake8 (==3.8) ; extra == 'dev'
Requires-Dist: pep8-naming (==0.11) ; extra == 'dev'
Requires-Dist: pytest (==5.4) ; extra == 'dev'
Requires-Dist: tox (==3.16) ; extra == 'dev'
Requires-Dist: twine ; extra == 'dev'
Provides-Extra: doc
Requires-Dist: sphinx (==3.1) ; extra == 'doc'
Requires-Dist: sphinx-autodoc-typehints (==1.11) ; extra == 'doc'
Requires-Dist: sphinx-copybutton0.2 ; extra == 'doc'
Requires-Dist: sphinx-rtd-theme (==0.4) ; extra == 'doc'
Requires-Dist: sphinx-toggleprompt (==0.0.2) ; extra == 'doc'
